LICENSE
README.md
pyproject.toml
setup.cfg
setup.py
pyclickhouse/Connection.py
pyclickhouse/Cursor.py
pyclickhouse/FilterableCache.py
pyclickhouse/__init__.py
pyclickhouse/formatter.py
pyclickhouse3.egg-info/PKG-INFO
pyclickhouse3.egg-info/SOURCES.txt
pyclickhouse3.egg-info/dependency_links.txt
pyclickhouse3.egg-info/not-zip-safe
pyclickhouse3.egg-info/requires.txt
pyclickhouse3.egg-info/top_level.txt
test/test_compatibility.py
test/test_map.py
test/test_new.py
test/test_simple.py
test/test_variant.py