Metadata-Version: 1.1
Name: pyclickhouse3
Version: 0.10.0
Summary: Clickhouse Python driver with an API roughly resembling Python DB API 2.0 specification.
Home-page: https://github.com/mfridental/PyClickhouse
Author: Maxim Fridental (Maintainer)
Author-email: maxim@fridental.de
License: Apache2
Download-URL: https://github.com/mfridental/PyClickhouse/archive/0.10.0.tar.gz
Keywords: Clickhouse,Database,Driver
Platform: UNKNOWN
